yolov5_sp/__init__.py
yolov5_sp/yolov5.py
yolov5_sp/configs/__init__.py
yolov5_sp/models/__init__.py
yolov5_sp/models/common.py
yolov5_sp/models/experimental.py
yolov5_sp/models/yolo.py
yolov5_sp/utils/__init__.py
yolov5_sp/utils/activations.py
yolov5_sp/utils/augmentations.py
yolov5_sp/utils/autoanchor.py
yolov5_sp/utils/callbacks.py
yolov5_sp/utils/datasets.py
yolov5_sp/utils/downloads.py
yolov5_sp/utils/general.py
yolov5_sp/utils/log.py
yolov5_sp/utils/loss.py
yolov5_sp/utils/metrics.py
yolov5_sp/utils/plots.py
yolov5_sp/utils/resize_and_pad.py
yolov5_sp/utils/torch_utils.py
yolov5_sp-1.0.3.dist-info/METADATA
yolov5_sp-1.0.3.dist-info/WHEEL
yolov5_sp-1.0.3.dist-info/entry_points.txt
yolov5_sp-1.0.3.dist-info/license.txt
yolov5_sp-1.0.3.dist-info/top_level.txt
yolov5_sp-1.0.3.dist-info/RECORD
